microsoft_login_button/__init__.py
microsoft_login_button/example.py
microsoft_login_button/build/asset-manifest.json
microsoft_login_button/build/bootstrap.min.css
microsoft_login_button/build/index.html
microsoft_login_button/build/static/js/main.09461a26.js
microsoft_login_button/build/static/js/main.09461a26.js.LICENSE.txt
microsoft_login_button/build/static/js/main.09461a26.js.map
msal_streamlit_button-1.0.2.dist-info/METADATA
msal_streamlit_button-1.0.2.dist-info/WHEEL
msal_streamlit_button-1.0.2.dist-info/top_level.txt
msal_streamlit_button-1.0.2.dist-info/RECORD
