Metadata-Version: 2.1
Name: msal-streamlit-button
Version: 1.0.2
Summary: Streamlit component that allows you to create a microsoft login Button
Home-page: 
Author: Alia Shiraz
Author-email: aliashiraz05@gmail.com
Requires-Python: >=3.7
Requires-Dist: streamlit>=1.3
Provides-Extra: devel
Requires-Dist: wheel; extra == "devel"
Requires-Dist: pytest==7.4.0; extra == "devel"
Requires-Dist: playwright==1.48.0; extra == "devel"
Requires-Dist: requests==2.31.0; extra == "devel"
Requires-Dist: pytest-playwright-snapshot==1.0; extra == "devel"
Requires-Dist: pytest-rerunfailures==12.0; extra == "devel"
